qwiic_button.py
sparkfun_qwiic_button-2.0.1.dist-info/LICENSE
sparkfun_qwiic_button-2.0.1.dist-info/METADATA
sparkfun_qwiic_button-2.0.1.dist-info/WHEEL
sparkfun_qwiic_button-2.0.1.dist-info/top_level.txt
sparkfun_qwiic_button-2.0.1.dist-info/RECORD
